setup.py
jupyterlab_horizon_theme/__init__.py
jupyterlab_horizon_theme/_version.py
jupyterlab_purple_wave/_version.py
jupyterlab_purple_wave_theme/labextension/package.json
jupyterlab_purple_wave_theme/labextension/static/568.9f0e86c070817b9e94e0.js
jupyterlab_purple_wave_theme/labextension/static/remoteEntry.02ebc50dcff848519eb2.js
jupyterlab_purple_wave_theme/labextension/static/style.js
jupyterlab_purple_wave_theme/labextension/static/third-party-licenses.json
jupyterlab_purple_wave_theme/labextension/themes/@arnos-stuff/jupyterlab-purple-wave-theme/2967dd73df838d2a2d390a638c6d7cfe9cd60c5ee2e162d8a1c10a70ea742b5c.ttf
jupyterlab_purple_wave_theme/labextension/themes/@arnos-stuff/jupyterlab-purple-wave-theme/5992ab9640e2df491b2f609467b1de60e8bc39b2c28db184342a0592d98f6117.ttf
jupyterlab_purple_wave_theme/labextension/themes/@arnos-stuff/jupyterlab-purple-wave-theme/80922933add5aaad3870ade70f2a414a57327a7990ef935345ecb7a1d579e3c0.ttf
jupyterlab_purple_wave_theme/labextension/themes/@arnos-stuff/jupyterlab-purple-wave-theme/dcf9c1dc1db7d66f0778a1b3e84856279e4839d2221b427509c3c969101b7a4e.png
jupyterlab_purple_wave_theme/labextension/themes/@arnos-stuff/jupyterlab-purple-wave-theme/index.css
jupyterlab_purple_wave_theme/labextension/themes/@arnos-stuff/jupyterlab-purple-wave-theme/index.js
ui-tests/jupyter_server_test_config.py
jupyterlab_purple_wave_theme-3.1.3.data/data/share/jupyter/labextensions/@mohirio/jupyterlab-horizon-theme/package.json
jupyterlab_purple_wave_theme-3.1.3.data/data/share/jupyter/labextensions/@mohirio/jupyterlab-horizon-theme/static/568.9f0e86c070817b9e94e0.js
jupyterlab_purple_wave_theme-3.1.3.data/data/share/jupyter/labextensions/@mohirio/jupyterlab-horizon-theme/static/remoteEntry.02ebc50dcff848519eb2.js
jupyterlab_purple_wave_theme-3.1.3.data/data/share/jupyter/labextensions/@mohirio/jupyterlab-horizon-theme/static/style.js
jupyterlab_purple_wave_theme-3.1.3.dist-info/METADATA
jupyterlab_purple_wave_theme-3.1.3.dist-info/WHEEL
jupyterlab_purple_wave_theme-3.1.3.dist-info/licenses/LICENSE
jupyterlab_purple_wave_theme-3.1.3.dist-info/RECORD
