Metadata-Version: 2.1
Name: jupyterlab_purple_wave_theme
Version: 3.1.3
Summary: VSCode Purple Wave Custom Theme for JupyterLab
Project-URL: Homepage, https://github.com/arnos-stuff/jupyterlab-purple-wave-theme
Project-URL: Bug Tracker, https://github.com/arnos-stuff/jupyterlab-purple-wave-theme
Project-URL: Repository, https://github.com/arnos-stuff/jupyterlab-purple-wave-theme.git
Author-email: Arno V <bcda0276@gmail.com>
License: Copyright (c) 2019, Mohammad Almogbel
License-File: LICENSE
Classifier: Framework :: Jupyter
Classifier: Framework :: Jupyter :: JupyterLab
Classifier: Framework :: Jupyter :: JupyterLab :: 3
Classifier: Framework :: Jupyter :: JupyterLab :: Extensions
Classifier: Framework :: Jupyter :: JupyterLab :: Extensions :: Prebuilt
Classifier: License :: OSI Approved :: BSD License
Classifier: Programming Language :: Python
Classifier: Programming Language :: Python :: 3
Classifier: Programming Language :: Python :: 3.7
Classifier: Programming Language :: Python :: 3.8
Classifier: Programming Language :: Python :: 3.9
Classifier: Programming Language :: Python :: 3.10
Requires-Python: >=3.7
Provides-Extra: test
Requires-Dist: coverage; extra == 'test'
Requires-Dist: pytest; extra == 'test'
Requires-Dist: pytest-asyncio; extra == 'test'
Requires-Dist: pytest-cov; extra == 'test'
Requires-Dist: pytest-tornasync; extra == 'test'
